pyarazzo-0.0.2.dist-info/METADATA
pyarazzo-0.0.2.dist-info/WHEEL
pyarazzo-0.0.2.dist-info/entry_points.txt
pyarazzo-0.0.2.dist-info/licenses/LICENSE
pyarazzo/__init__.py
pyarazzo/__main__.py
pyarazzo/cli.py
pyarazzo/config.py
pyarazzo/debug.py
pyarazzo/doc/__init__.py
pyarazzo/doc/cmd.py
pyarazzo/doc/generator.py
pyarazzo/exceptions.py
pyarazzo/model/__init__.py
pyarazzo/model/arazzo.py
pyarazzo/model/openapi.py
pyarazzo/schema.yaml
pyarazzo/utils.py
pyarazzo-0.0.2.dist-info/RECORD
